client_utils/__init__.py
client_utils/base_client.py
scramjet_client_utils-1.1.1.dist-info/METADATA
scramjet_client_utils-1.1.1.dist-info/WHEEL
scramjet_client_utils-1.1.1.dist-info/top_level.txt
scramjet_client_utils-1.1.1.dist-info/RECORD
