Metadata-Version: 2.1
Name: scramjet-client-utils
Version: 1.1.1
Home-page: https://github.com/scramjetorg/api-client-python/tree/main/client_utils
Author: Scramjet
Author-email: open-source@scramjet.org
Requires-Python: >=3.9,<4.0
Requires-Dist: aiohttp <4.0.0,>=3.8.3
Requires-Dist: url-normalize <2.0.0,>=1.4.3
